[{"client_id":5524,"income":58138.0},{"client_id":2174,"income":46344.0},{"client_id":4141,"income":71613.0},{"client_id":6182,"income":26646.0},{"client_id":5324,"income":58293.0},{"client_id":7446,"income":62513.0},{"client_id":965,"income":55635.0},{"client_id":6177,"income":33454.0},{"client_id":4855,"income":30351.0},{"client_id":5899,"income":5648.0},{"client_id":1994,"income":null},{"client_id":387,"income":7500.0},{"client_id":2125,"income":63033.0},{"client_id":8180,"income":59354.0},{"client_id":2569,"income":17323.0},{"client_id":2114,"income":82800.0},{"client_id":9736,"income":41850.0},{"client_id":4939,"income":37760.0},{"client_id":6565,"income":76995.0},{"client_id":2278,"income":33812.0},{"client_id":9360,"income":37040.0},{"client_id":5376,"income":2447.0},{"client_id":1993,"income":58607.0},{"client_id":4047,"income":65324.0},{"client_id":1409,"income":40689.0},{"client_id":7892,"income":18589.0},{"client_id":2404,"income":53359.0},{"client_id":5255,"income":null},{"client_id":9422,"income":38360.0},{"client_id":1966,"income":84618.0},{"client_id":6864,"income":10979.0},{"client_id":3033,"income":38620.0},{"client_id":5710,"income":40548.0},{"client_id":7373,"income":46610.0},{"client_id":8755,"income":68657.0},{"client_id":10738,"income":49389.0},{"client_id":4339,"income":67353.0},{"client_id":10755,"income":23718.0},{"client_id":8595,"income":42429.0},{"client_id":2968,"income":48948.0},{"client_id":8601,"income":80011.0},{"client_id":503,"income":20559.0},{"client_id":8430,"income":21994.0},{"client_id":7281,"income":null},{"client_id":2139,"income":7500.0},{"client_id":1371,"income":79941.0},{"client_id":9909,"income":7500.0},{"client_id":7286,"income":41728.0},{"client_id":7244,"income":null},{"client_id":6566,"income":72550.0},{"client_id":8614,"income":65486.0},{"client_id":4114,"income":79143.0},{"client_id":1331,"income":35790.0},{"client_id":2225,"income":82582.0},{"client_id":9381,"income":66373.0},{"client_id":6260,"income":82384.0},{"client_id":10383,"income":70287.0},{"client_id":7437,"income":27938.0},{"client_id":8557,"income":null},{"client_id":8375,"income":55954.0},{"client_id":6853,"income":75777.0},{"client_id":3076,"income":66653.0},{"client_id":1012,"income":61823.0},{"client_id":6518,"income":67680.0},{"client_id":4137,"income":70666.0},{"client_id":8082,"income":25721.0},{"client_id":1386,"income":32474.0},{"client_id":9369,"income":88194.0},{"client_id":4477,"income":69096.0},{"client_id":1357,"income":74854.0},{"client_id":1402,"income":66991.0},{"client_id":10629,"income":null},{"client_id":6312,"income":65031.0},{"client_id":8132,"income":60631.0},{"client_id":1050,"income":28332.0},{"client_id":5846,"income":40246.0},{"client_id":1859,"income":75251.0},{"client_id":7503,"income":75825.0},{"client_id":10401,"income":26326.0},{"client_id":1618,"income":56046.0},{"client_id":3332,"income":29760.0},{"client_id":2261,"income":26304.0},{"client_id":5346,"income":23559.0},{"client_id":4119,"income":38620.0},{"client_id":535,"income":81361.0},{"client_id":5268,"income":29440.0},{"client_id":273,"income":36138.0},{"client_id":4452,"income":50388.0},{"client_id":8504,"income":79593.0},{"client_id":771,"income":54178.0},{"client_id":8996,"income":null},{"client_id":9235,"income":null},{"client_id":5798,"income":null},{"client_id":11178,"income":42394.0},{"client_id":2230,"income":23626.0},{"client_id":7516,"income":30096.0},{"client_id":7247,"income":47916.0},{"client_id":11100,"income":51813.0},{"client_id":4646,"income":78497.0},{"client_id":3037,"income":50150.0},{"client_id":1473,"income":47823.0},{"client_id":1016,"income":34554.0},{"client_id":4518,"income":85693.0},{"client_id":9370,"income":65846.0},{"client_id":8908,"income":87195.0},{"client_id":8373,"income":24594.0},{"client_id":7533,"income":49096.0},{"client_id":2683,"income":52413.0},{"client_id":3629,"income":38557.0},{"client_id":10991,"income":89058.0},{"client_id":5077,"income":77298.0},{"client_id":7431,"income":68126.0},{"client_id":3267,"income":57288.0},{"client_id":999,"income":86037.0},{"client_id":9215,"income":43974.0},{"client_id":2286,"income":50785.0},{"client_id":1592,"income":90765.0},{"client_id":367,"income":36550.0},{"client_id":5234,"income":30753.0},{"client_id":9862,"income":21918.0},{"client_id":9805,"income":56129.0},{"client_id":6205,"income":32557.0},{"client_id":8442,"income":19510.0},{"client_id":7386,"income":30992.0},{"client_id":7215,"income":101970.0},{"client_id":1491,"income":71488.0},{"client_id":11071,"income":79607.0},{"client_id":3381,"income":54348.0},{"client_id":8268,"income":null},{"client_id":11051,"income":77376.0},{"client_id":8026,"income":62998.0},{"client_id":433,"income":61331.0},{"client_id":9597,"income":73448.0},{"client_id":1295,"income":null},{"client_id":5290,"income":41551.0},{"client_id":1685,"income":62981.0},{"client_id":5342,"income":9548.0},{"client_id":9579,"income":33762.0},{"client_id":7660,"income":35860.0},{"client_id":1461,"income":36921.0},{"client_id":821,"income":92859.0},{"client_id":11084,"income":65104.0},{"client_id":8690,"income":86111.0},{"client_id":2937,"income":68352.0},{"client_id":9701,"income":41883.0},{"client_id":9949,"income":59809.0},{"client_id":10837,"income":23957.0},{"client_id":3120,"income":38547.0},{"client_id":5885,"income":35688.0},{"client_id":4050,"income":49605.0},{"client_id":3830,"income":59354.0},{"client_id":7987,"income":65747.0},{"client_id":7798,"income":46344.0},{"client_id":92,"income":34176.0},{"client_id":7055,"income":61010.0},{"client_id":10240,"income":69372.0},{"client_id":3025,"income":49967.0},{"client_id":9283,"income":60199.0},{"client_id":9970,"income":55375.0},{"client_id":2730,"income":80317.0},{"client_id":2795,"income":30523.0},{"client_id":9260,"income":70356.0},{"client_id":8182,"income":23228.0},{"client_id":10095,"income":74165.0},{"client_id":8475,"income":157243.0},{"client_id":4370,"income":43482.0},{"client_id":10573,"income":62551.0},{"client_id":3712,"income":52332.0},{"client_id":6637,"income":66951.0},{"client_id":3152,"income":26091.0},{"client_id":5610,"income":33456.0},{"client_id":6460,"income":28718.0},{"client_id":1349,"income":50447.0},{"client_id":1880,"income":53537.0},{"client_id":641,"income":52074.0},{"client_id":8717,"income":80427.0},{"client_id":10314,"income":83837.0},{"client_id":10854,"income":38853.0},{"client_id":10492,"income":38285.0},{"client_id":6935,"income":78497.0},{"client_id":7698,"income":51650.0},{"client_id":3559,"income":16248.0},{"client_id":10562,"income":66835.0},{"client_id":10796,"income":30477.0},{"client_id":2563,"income":28249.0},{"client_id":3518,"income":25271.0},{"client_id":5823,"income":32303.0},{"client_id":3934,"income":61286.0},{"client_id":6982,"income":74068.0},{"client_id":6431,"income":45759.0},{"client_id":9733,"income":24882.0},{"client_id":5602,"income":66973.0},{"client_id":7829,"income":36640.0},{"client_id":1324,"income":38872.0},{"client_id":326,"income":51148.0},{"client_id":7224,"income":31353.0},{"client_id":6999,"income":69661.0},{"client_id":9938,"income":80067.0},{"client_id":6422,"income":86718.0},{"client_id":3182,"income":46854.0},{"client_id":7300,"income":69142.0},{"client_id":10424,"income":75922.0},{"client_id":8727,"income":63693.0},{"client_id":2798,"income":102160.0},{"client_id":1030,"income":40637.0},{"client_id":624,"income":18890.0},{"client_id":5176,"income":29604.0},{"client_id":5552,"income":48721.0},{"client_id":868,"income":44794.0},{"client_id":380,"income":64497.0},{"client_id":2677,"income":46097.0},{"client_id":6521,"income":77972.0},{"client_id":6927,"income":44377.0},{"client_id":2877,"income":46014.0},{"client_id":0,"income":70951.0},{"client_id":1584,"income":41443.0},{"client_id":7264,"income":52195.0},{"client_id":6274,"income":83790.0},{"client_id":1377,"income":44551.0},{"client_id":454,"income":69508.0},{"client_id":1755,"income":45204.0},{"client_id":2075,"income":72460.0},{"client_id":4785,"income":77622.0},{"client_id":9076,"income":30732.0},{"client_id":7079,"income":63887.0},{"client_id":4653,"income":42011.0},{"client_id":7375,"income":51369.0},{"client_id":709,"income":51537.0},{"client_id":460,"income":79930.0},{"client_id":3726,"income":34320.0},{"client_id":6798,"income":37070.0},{"client_id":5341,"income":81975.0},{"client_id":1606,"income":38590.0},{"client_id":9617,"income":15033.0},{"client_id":3233,"income":62745.0},{"client_id":89,"income":22212.0},{"client_id":2936,"income":23661.0},{"client_id":9449,"income":79761.0},{"client_id":7297,"income":7500.0},{"client_id":11004,"income":60182.0},{"client_id":313,"income":73455.0},{"client_id":9940,"income":64961.0},{"client_id":10735,"income":22804.0},{"client_id":9529,"income":73687.0},{"client_id":6439,"income":61074.0},{"client_id":7411,"income":31686.0},{"client_id":2176,"income":80134.0},{"client_id":9265,"income":75027.0},{"client_id":8867,"income":67546.0},{"client_id":8932,"income":65176.0},{"client_id":10236,"income":31160.0},{"client_id":6340,"income":29938.0},{"client_id":10089,"income":102692.0},{"client_id":2227,"income":26490.0},{"client_id":10992,"income":75702.0},{"client_id":5304,"income":30899.0},{"client_id":309,"income":63342.0},{"client_id":3406,"income":45989.0},{"client_id":2661,"income":18701.0},{"client_id":3153,"income":40737.0},{"client_id":10264,"income":15287.0},{"client_id":1184,"income":69674.0},{"client_id":4200,"income":44159.0},{"client_id":9396,"income":37717.0},{"client_id":2387,"income":43776.0},{"client_id":6690,"income":38179.0},{"client_id":1225,"income":80124.0},{"client_id":9703,"income":38097.0},{"client_id":291,"income":72940.0},{"client_id":4557,"income":22070.0},{"client_id":2379,"income":69267.0},{"client_id":5726,"income":31788.0},{"client_id":3066,"income":61905.0},{"client_id":6336,"income":29315.0},{"client_id":10967,"income":33378.0},{"client_id":2304,"income":66313.0},{"client_id":3445,"income":60714.0},{"client_id":7828,"income":77882.0},{"client_id":3762,"income":69867.0},{"client_id":4391,"income":63841.0},{"client_id":4669,"income":24480.0},{"client_id":10144,"income":51369.0},{"client_id":8652,"income":37760.0},{"client_id":1672,"income":65640.0},{"client_id":8962,"income":44319.0},{"client_id":9974,"income":30631.0},{"client_id":10983,"income":75278.0},{"client_id":8148,"income":50898.0},{"client_id":10102,"income":79946.0},{"client_id":4697,"income":35416.0},{"client_id":9262,"income":32414.0},{"client_id":7254,"income":38361.0},{"client_id":4543,"income":82497.0},{"client_id":4927,"income":16626.0},{"client_id":10451,"income":29672.0},{"client_id":2926,"income":55951.0},{"client_id":2874,"income":35388.0},{"client_id":9738,"income":42386.0},{"client_id":7119,"income":68627.0},{"client_id":3924,"income":57912.0},{"client_id":5827,"income":35246.0},{"client_id":5596,"income":58821.0},{"client_id":10812,"income":46377.0},{"client_id":1717,"income":39747.0},{"client_id":9491,"income":23976.0},{"client_id":9274,"income":80950.0},{"client_id":6609,"income":27038.0},{"client_id":6963,"income":77457.0},{"client_id":4440,"income":64100.0},{"client_id":1379,"income":42670.0},{"client_id":10032,"income":12571.0},{"client_id":2826,"income":22574.0},{"client_id":2437,"income":null},{"client_id":6320,"income":70893.0},{"client_id":3050,"income":54198.0},{"client_id":231,"income":28839.0},{"client_id":2392,"income":40321.0},{"client_id":9478,"income":66503.0},{"client_id":113,"income":30833.0},{"client_id":2863,"income":null},{"client_id":1802,"income":64795.0},{"client_id":520,"income":34421.0},{"client_id":8275,"income":47025.0},{"client_id":9750,"income":64325.0},{"client_id":2607,"income":40464.0},{"client_id":7214,"income":62187.0},{"client_id":5835,"income":14849.0},{"client_id":3896,"income":27255.0},{"client_id":10350,"income":54432.0},{"client_id":7786,"income":29999.0},{"client_id":2861,"income":24072.0},{"client_id":663,"income":33996.0},{"client_id":10675,"income":66334.0},{"client_id":2521,"income":35178.0},{"client_id":9592,"income":22010.0},{"client_id":10151,"income":62204.0},{"client_id":7381,"income":75693.0},{"client_id":4099,"income":30675.0},{"client_id":9560,"income":83003.0},{"client_id":1150,"income":83532.0},{"client_id":10172,"income":68655.0},{"client_id":11191,"income":41411.0},{"client_id":9707,"income":55212.0},{"client_id":6245,"income":59292.0},{"client_id":8234,"income":27190.0},{"client_id":1411,"income":82623.0},{"client_id":8553,"income":44300.0},{"client_id":1826,"income":84835.0},{"client_id":8842,"income":30372.0},{"client_id":11030,"income":33181.0},{"client_id":2579,"income":71113.0},{"client_id":175,"income":71952.0},{"client_id":9185,"income":69759.0},{"client_id":11056,"income":72099.0},{"client_id":9365,"income":60000.0},{"client_id":6201,"income":38643.0},{"client_id":2061,"income":50737.0},{"client_id":6184,"income":68462.0},{"client_id":6142,"income":65073.0},{"client_id":4107,"income":46681.0},{"client_id":7274,"income":78618.0},{"client_id":9336,"income":62187.0},{"client_id":2958,"income":28442.0},{"client_id":933,"income":37717.0},{"client_id":5837,"income":51479.0},{"client_id":10704,"income":54803.0},{"client_id":5125,"income":79530.0},{"client_id":4432,"income":31615.0},{"client_id":5955,"income":72025.0},{"client_id":2928,"income":52614.0},{"client_id":5680,"income":35684.0},{"client_id":10313,"income":48178.0},{"client_id":2557,"income":29548.0},{"client_id":1245,"income":63810.0},{"client_id":1519,"income":38578.0},{"client_id":10703,"income":46098.0},{"client_id":1726,"income":22585.0},{"client_id":4459,"income":30279.0},{"client_id":1729,"income":66426.0},{"client_id":1517,"income":30822.0},{"client_id":2098,"income":33581.0},{"client_id":9543,"income":19986.0},{"client_id":6878,"income":27421.0},{"client_id":3310,"income":35688.0},{"client_id":2724,"income":36143.0},{"client_id":948,"income":10245.0},{"client_id":6720,"income":43795.0},{"client_id":6202,"income":63381.0},{"client_id":2066,"income":38823.0},{"client_id":9799,"income":83664.0},{"client_id":8318,"income":90300.0},{"client_id":5642,"income":62499.0},{"client_id":2669,"income":74293.0},{"client_id":455,"income":51012.0},{"client_id":7683,"income":70777.0},{"client_id":3428,"income":68682.0},{"client_id":7414,"income":43824.0},{"client_id":6354,"income":15345.0},{"client_id":798,"income":23442.0},{"client_id":8213,"income":14515.0},{"client_id":2488,"income":31395.0},{"client_id":9999,"income":75276.0},{"client_id":7617,"income":42373.0},{"client_id":615,"income":30507.0},{"client_id":2552,"income":55521.0},{"client_id":194,"income":48006.0},{"client_id":3645,"income":27213.0},{"client_id":8890,"income":65808.0},{"client_id":5049,"income":30351.0},{"client_id":9973,"income":50437.0},{"client_id":7301,"income":23616.0},{"client_id":10882,"income":53858.0},{"client_id":7030,"income":66465.0},{"client_id":7422,"income":46923.0},{"client_id":3523,"income":75072.0},{"client_id":7106,"income":75865.0},{"client_id":6504,"income":19789.0},{"client_id":5067,"income":80134.0},{"client_id":4216,"income":91065.0},{"client_id":8581,"income":49505.0},{"client_id":5929,"income":37401.0},{"client_id":3129,"income":30096.0},{"client_id":6528,"income":18492.0},{"client_id":1361,"income":82584.0},{"client_id":6932,"income":93027.0},{"client_id":7284,"income":48686.0},{"client_id":1340,"income":92910.0},{"client_id":8746,"income":75433.0},{"client_id":5987,"income":10404.0},{"client_id":3767,"income":61314.0},{"client_id":3725,"income":84865.0},{"client_id":4324,"income":42387.0},{"client_id":238,"income":67309.0},{"client_id":6694,"income":75236.0},{"client_id":498,"income":30015.0},{"client_id":9347,"income":50943.0},{"client_id":9699,"income":67272.0},{"client_id":10664,"income":51529.0},{"client_id":5455,"income":32011.0},{"client_id":456,"income":7500.0},{"client_id":5012,"income":28691.0},{"client_id":7495,"income":56223.0},{"client_id":5029,"income":18100.0},{"client_id":10642,"income":30279.0},{"client_id":2106,"income":20130.0},{"client_id":10364,"income":23295.0},{"client_id":5954,"income":42618.0},{"client_id":1137,"income":81246.0},{"client_id":2541,"income":24027.0},{"client_id":1142,"income":55707.0},{"client_id":2276,"income":57959.0},{"client_id":2807,"income":56796.0},{"client_id":6471,"income":36230.0},{"client_id":6131,"income":70829.0},{"client_id":6233,"income":65991.0},{"client_id":4148,"income":38988.0},{"client_id":4947,"income":89572.0},{"client_id":3225,"income":42207.0},{"client_id":7540,"income":50300.0},{"client_id":10648,"income":66664.0},{"client_id":1992,"income":60597.0},{"client_id":7851,"income":70165.0},{"client_id":8594,"income":50520.0},{"client_id":7059,"income":80124.0},{"client_id":2815,"income":33183.0},{"client_id":2416,"income":66582.0},{"client_id":7999,"income":75261.0},{"client_id":9213,"income":31880.0},{"client_id":9697,"income":53790.0},{"client_id":3916,"income":49269.0},{"client_id":2021,"income":61456.0},{"client_id":1581,"income":37406.0},{"client_id":564,"income":56937.0},{"client_id":6619,"income":38415.0},{"client_id":9081,"income":20518.0},{"client_id":178,"income":62503.0},{"client_id":916,"income":41644.0},{"client_id":5512,"income":55842.0},{"client_id":8970,"income":62010.0},{"client_id":10581,"income":41124.0},{"client_id":5300,"income":38961.0},{"client_id":5154,"income":37760.0},{"client_id":8346,"income":32233.0},{"client_id":1676,"income":43057.0},{"client_id":9286,"income":83151.0},{"client_id":2426,"income":78825.0},{"client_id":5172,"income":65104.0},{"client_id":5562,"income":60093.0},{"client_id":3436,"income":14045.0},{"client_id":3921,"income":28457.0},{"client_id":3403,"income":78952.0},{"client_id":22,"income":46310.0},{"client_id":10965,"income":76005.0},{"client_id":9426,"income":58308.0},{"client_id":6605,"income":55614.0},{"client_id":3136,"income":59432.0},{"client_id":8737,"income":55563.0},{"client_id":11088,"income":78642.0},{"client_id":716,"income":67911.0},{"client_id":466,"income":65275.0},{"client_id":9135,"income":27203.0},{"client_id":10623,"income":48330.0},{"client_id":8151,"income":24279.0},{"client_id":5140,"income":64355.0},{"client_id":10160,"income":50943.0},{"client_id":4945,"income":53653.0},{"client_id":10584,"income":65665.0},{"client_id":6071,"income":81217.0},{"client_id":3386,"income":34935.0},{"client_id":8939,"income":61250.0},{"client_id":9925,"income":39665.0},{"client_id":4320,"income":60152.0},{"client_id":5389,"income":48920.0},{"client_id":6036,"income":89120.0},{"client_id":182,"income":44124.0},{"client_id":203,"income":81169.0},{"client_id":11025,"income":36443.0},{"client_id":10203,"income":26095.0},{"client_id":4607,"income":71367.0},{"client_id":3711,"income":80184.0},{"client_id":3696,"income":30630.0},{"client_id":2532,"income":73454.0},{"client_id":9214,"income":42691.0},{"client_id":4943,"income":70503.0},{"client_id":35,"income":25545.0},{"client_id":2258,"income":32880.0},{"client_id":4322,"income":77863.0},{"client_id":713,"income":50353.0},{"client_id":4702,"income":61839.0},{"client_id":3281,"income":49154.0},{"client_id":702,"income":47682.0},{"client_id":2004,"income":72679.0},{"client_id":4769,"income":57954.0},{"client_id":4437,"income":65316.0},{"client_id":8724,"income":28567.0},{"client_id":10741,"income":47352.0},{"client_id":1991,"income":44931.0},{"client_id":6931,"income":76982.0},{"client_id":11096,"income":57247.0},{"client_id":304,"income":22944.0},{"client_id":3665,"income":25315.0},{"client_id":10591,"income":43638.0},{"client_id":5036,"income":42710.0},{"client_id":5547,"income":84169.0},{"client_id":7822,"income":54058.0},{"client_id":8541,"income":24683.0},{"client_id":10955,"income":85620.0},{"client_id":4368,"income":47850.0},{"client_id":9671,"income":19514.0},{"client_id":2256,"income":27159.0},{"client_id":4279,"income":39548.0},{"client_id":5371,"income":21474.0},{"client_id":9240,"income":60504.0},{"client_id":9460,"income":22419.0},{"client_id":9504,"income":81698.0},{"client_id":8692,"income":43462.0},{"client_id":448,"income":54880.0},{"client_id":8314,"income":79908.0},{"client_id":8420,"income":15315.0},{"client_id":3174,"income":87771.0},{"client_id":7685,"income":33039.0},{"client_id":3179,"income":81741.0},{"client_id":9780,"income":71499.0},{"client_id":10681,"income":62466.0},{"client_id":10232,"income":48799.0},{"client_id":4184,"income":52157.0},{"client_id":9120,"income":66565.0},{"client_id":891,"income":29298.0},{"client_id":10381,"income":47691.0},{"client_id":3525,"income":38200.0},{"client_id":6818,"income":44989.0},{"client_id":3526,"income":38443.0},{"client_id":8181,"income":38593.0},{"client_id":1029,"income":64413.0},{"client_id":7369,"income":36959.0},{"client_id":2574,"income":61996.0},{"client_id":8159,"income":51287.0},{"client_id":1160,"income":13260.0},{"client_id":10242,"income":47472.0},{"client_id":5253,"income":54603.0},{"client_id":5966,"income":45207.0},{"client_id":5314,"income":40689.0},{"client_id":5081,"income":47821.0},{"client_id":5123,"income":27450.0},{"client_id":5756,"income":39453.0},{"client_id":8036,"income":26850.0},{"client_id":9058,"income":79800.0},{"client_id":5057,"income":61794.0},{"client_id":254,"income":53863.0},{"client_id":4179,"income":24221.0},{"client_id":3710,"income":39684.0},{"client_id":7627,"income":92163.0},{"client_id":4501,"income":69882.0},{"client_id":6424,"income":33178.0},{"client_id":3075,"income":59973.0},{"client_id":4992,"income":17459.0},{"client_id":5252,"income":23910.0},{"client_id":7444,"income":42169.0},{"client_id":6919,"income":26224.0},{"client_id":3537,"income":31089.0},{"client_id":10277,"income":30081.0},{"client_id":2453,"income":62807.0},{"client_id":7972,"income":72906.0},{"client_id":895,"income":61467.0},{"client_id":1177,"income":49618.0},{"client_id":7141,"income":21888.0},{"client_id":7232,"income":42429.0},{"client_id":8477,"income":26150.0},{"client_id":2457,"income":30801.0},{"client_id":988,"income":81168.0},{"client_id":7930,"income":26877.0},{"client_id":4587,"income":45006.0},{"client_id":6682,"income":18978.0},{"client_id":6222,"income":22574.0},{"client_id":10299,"income":48240.0},{"client_id":3083,"income":45837.0},{"client_id":8953,"income":35791.0},{"client_id":1503,"income":162397.0},{"client_id":8650,"income":54162.0},{"client_id":10862,"income":30522.0},{"client_id":2782,"income":54456.0},{"client_id":6941,"income":31632.0},{"client_id":10972,"income":72298.0},{"client_id":10708,"income":36975.0},{"client_id":6583,"income":72635.0},{"client_id":3641,"income":13624.0},{"client_id":10156,"income":84196.0},{"client_id":4299,"income":70971.0},{"client_id":3469,"income":34487.0},{"client_id":5063,"income":28769.0},{"client_id":10727,"income":69084.0},{"client_id":9624,"income":65488.0},{"client_id":5156,"income":62466.0},{"client_id":4376,"income":32218.0},{"client_id":8923,"income":83917.0},{"client_id":8461,"income":46102.0},{"client_id":6945,"income":84574.0},{"client_id":944,"income":56181.0},{"client_id":1907,"income":63120.0},{"client_id":701,"income":73691.0},{"client_id":3856,"income":63381.0},{"client_id":4149,"income":76140.0},{"client_id":2131,"income":62859.0},{"client_id":2942,"income":45906.0},{"client_id":1173,"income":77632.0},{"client_id":4381,"income":46463.0},{"client_id":4611,"income":105471.0},{"client_id":3376,"income":55282.0},{"client_id":4679,"income":78710.0},{"client_id":10928,"income":66886.0},{"client_id":4248,"income":98777.0},{"client_id":6728,"income":29103.0},{"client_id":6661,"income":67445.0},{"client_id":4725,"income":50616.0},{"client_id":3277,"income":49431.0},{"client_id":5555,"income":153924.0},{"client_id":2564,"income":61278.0},{"client_id":946,"income":26490.0},{"client_id":3867,"income":73059.0},{"client_id":6940,"income":46734.0},{"client_id":55,"income":56253.0},{"client_id":7093,"income":19986.0},{"client_id":5084,"income":58330.0},{"client_id":1777,"income":25965.0},{"client_id":8162,"income":14661.0},{"client_id":10826,"income":18690.0},{"client_id":8754,"income":45068.0},{"client_id":1987,"income":21063.0},{"client_id":11007,"income":29187.0},{"client_id":7426,"income":54690.0},{"client_id":9153,"income":59304.0},{"client_id":10379,"income":59247.0},{"client_id":9204,"income":66731.0},{"client_id":3197,"income":77353.0},{"client_id":2920,"income":52614.0},{"client_id":6961,"income":26751.0},{"client_id":4673,"income":81300.0},{"client_id":9937,"income":70337.0},{"client_id":8779,"income":36145.0},{"client_id":9596,"income":65295.0},{"client_id":2891,"income":68118.0},{"client_id":4910,"income":68743.0},{"client_id":75,"income":41039.0},{"client_id":10120,"income":38946.0},{"client_id":6327,"income":65777.0},{"client_id":10142,"income":66476.0},{"client_id":9826,"income":86857.0},{"client_id":1501,"income":160803.0},{"client_id":10767,"income":77845.0},{"client_id":7279,"income":69476.0},{"client_id":7230,"income":50611.0},{"client_id":143,"income":61209.0},{"client_id":450,"income":42315.0},{"client_id":9316,"income":13084.0},{"client_id":6379,"income":47570.0},{"client_id":9239,"income":61923.0},{"client_id":8315,"income":34824.0},{"client_id":2868,"income":26518.0},{"client_id":10888,"income":45938.0},{"client_id":1277,"income":78468.0},{"client_id":9977,"income":78901.0},{"client_id":10196,"income":71427.0},{"client_id":6384,"income":71022.0},{"client_id":8029,"income":90247.0},{"client_id":968,"income":41335.0},{"client_id":6988,"income":71952.0},{"client_id":4472,"income":35682.0},{"client_id":6991,"income":43185.0},{"client_id":3336,"income":66375.0},{"client_id":4301,"income":35178.0},{"client_id":1940,"income":25252.0},{"client_id":1272,"income":55250.0},{"client_id":1388,"income":33249.0},{"client_id":1044,"income":58398.0},{"client_id":6969,"income":50272.0},{"client_id":10479,"income":76618.0},{"client_id":3619,"income":87305.0},{"client_id":1715,"income":25851.0},{"client_id":10159,"income":58710.0},{"client_id":1463,"income":45160.0},{"client_id":5114,"income":74806.0},{"client_id":4990,"income":59111.0},{"client_id":4329,"income":18988.0},{"client_id":10936,"income":72190.0},{"client_id":4692,"income":7500.0},{"client_id":7212,"income":44794.0},{"client_id":6086,"income":80395.0},{"client_id":437,"income":75012.0},{"client_id":11171,"income":56962.0},{"client_id":11101,"income":89891.0},{"client_id":5329,"income":35946.0},{"client_id":610,"income":53593.0},{"client_id":9384,"income":66373.0},{"client_id":5956,"income":45072.0},{"client_id":10430,"income":89694.0},{"client_id":7875,"income":72025.0},{"client_id":7072,"income":67432.0},{"client_id":6255,"income":70545.0},{"client_id":6516,"income":17487.0},{"client_id":5564,"income":62882.0},{"client_id":5682,"income":64108.0},{"client_id":7458,"income":34941.0},{"client_id":5237,"income":48767.0},{"client_id":7761,"income":38702.0},{"client_id":5278,"income":82224.0},{"client_id":3560,"income":83844.0},{"client_id":7235,"income":17003.0},{"client_id":10548,"income":71163.0},{"client_id":2281,"income":33697.0},{"client_id":4073,"income":63564.0},{"client_id":6974,"income":83443.0},{"client_id":7938,"income":51518.0},{"client_id":7094,"income":58330.0},{"client_id":3667,"income":80952.0},{"client_id":7723,"income":75507.0},{"client_id":3870,"income":63855.0},{"client_id":4012,"income":62220.0},{"client_id":5909,"income":58512.0},{"client_id":10470,"income":40662.0},{"client_id":6488,"income":38829.0},{"client_id":10270,"income":35523.0},{"client_id":6887,"income":79146.0},{"client_id":6406,"income":78285.0},{"client_id":7573,"income":31626.0},{"client_id":4508,"income":75127.0},{"client_id":221,"income":48726.0},{"client_id":5331,"income":74985.0},{"client_id":1911,"income":67430.0},{"client_id":20,"income":46891.0},{"client_id":8786,"income":62058.0},{"client_id":10582,"income":72063.0},{"client_id":1915,"income":78939.0},{"client_id":8897,"income":42720.0},{"client_id":2371,"income":33622.0},{"client_id":4303,"income":6835.0},{"client_id":6825,"income":41452.0},{"client_id":1072,"income":40760.0},{"client_id":4964,"income":74250.0},{"client_id":2461,"income":51124.0},{"client_id":10736,"income":72258.0},{"client_id":3194,"income":71466.0},{"client_id":10839,"income":36283.0},{"client_id":49,"income":20587.0},{"client_id":4290,"income":30467.0},{"client_id":10219,"income":31590.0},{"client_id":4211,"income":20425.0},{"client_id":1135,"income":17144.0},{"client_id":6299,"income":42564.0},{"client_id":10846,"income":43783.0},{"client_id":347,"income":40780.0},{"client_id":6543,"income":62847.0},{"client_id":10446,"income":82017.0},{"client_id":3479,"income":16813.0},{"client_id":11075,"income":51267.0},{"client_id":4442,"income":46524.0},{"client_id":199,"income":45183.0},{"client_id":6722,"income":70421.0},{"client_id":796,"income":60161.0},{"client_id":3749,"income":73926.0},{"client_id":8523,"income":19329.0},{"client_id":310,"income":61872.0},{"client_id":8629,"income":46984.0},{"client_id":236,"income":34838.0},{"client_id":9930,"income":82716.0},{"client_id":3483,"income":48192.0},{"client_id":4599,"income":49681.0},{"client_id":7326,"income":56850.0},{"client_id":7352,"income":55267.0},{"client_id":2350,"income":59666.0},{"client_id":9145,"income":72504.0},{"client_id":2964,"income":26872.0},{"client_id":5585,"income":21359.0},{"client_id":9687,"income":73170.0},{"client_id":3732,"income":52750.0},{"client_id":6303,"income":91820.0},{"client_id":11176,"income":65968.0},{"client_id":2986,"income":30772.0},{"client_id":7462,"income":22507.0},{"client_id":3900,"income":65685.0},{"client_id":7034,"income":25804.0},{"client_id":9493,"income":76412.0},{"client_id":1143,"income":22063.0},{"client_id":1,"income":57091.0},{"client_id":3855,"income":22419.0},{"client_id":5536,"income":87771.0},{"client_id":5989,"income":78353.0},{"client_id":9499,"income":93404.0},{"client_id":6768,"income":37859.0},{"client_id":2150,"income":80995.0},{"client_id":6646,"income":16529.0},{"client_id":4887,"income":55412.0},{"client_id":8560,"income":48789.0},{"client_id":3321,"income":56575.0},{"client_id":11003,"income":25130.0},{"client_id":10402,"income":35441.0},{"client_id":9904,"income":71391.0},{"client_id":6141,"income":49494.0},{"client_id":5687,"income":81702.0},{"client_id":10856,"income":45889.0},{"client_id":5121,"income":56628.0},{"client_id":4186,"income":34026.0},{"client_id":368,"income":40049.0},{"client_id":3312,"income":34176.0},{"client_id":11121,"income":19419.0},{"client_id":5332,"income":82504.0},{"client_id":5848,"income":81205.0},{"client_id":10343,"income":61618.0},{"client_id":5935,"income":55284.0},{"client_id":2895,"income":49980.0},{"client_id":10262,"income":15072.0},{"client_id":7848,"income":49166.0},{"client_id":9477,"income":65324.0},{"client_id":4856,"income":82347.0},{"client_id":7186,"income":30843.0},{"client_id":5794,"income":46374.0},{"client_id":1456,"income":60474.0},{"client_id":4877,"income":38576.0},{"client_id":425,"income":55357.0},{"client_id":3007,"income":37758.0},{"client_id":1031,"income":85710.0},{"client_id":4297,"income":23228.0},{"client_id":807,"income":44602.0},{"client_id":9553,"income":7500.0},{"client_id":4271,"income":38683.0},{"client_id":4120,"income":49514.0},{"client_id":2036,"income":57906.0},{"client_id":115,"income":43456.0},{"client_id":4259,"income":19485.0},{"client_id":8687,"income":53172.0},{"client_id":2447,"income":30545.0},{"client_id":10140,"income":70123.0},{"client_id":9353,"income":62450.0},{"client_id":3623,"income":21675.0},{"client_id":738,"income":42395.0},{"client_id":7631,"income":61346.0},{"client_id":4789,"income":80812.0},{"client_id":773,"income":42835.0},{"client_id":10602,"income":39922.0},{"client_id":1446,"income":86424.0},{"client_id":3270,"income":17117.0},{"client_id":8443,"income":24762.0},{"client_id":9653,"income":35797.0},{"client_id":8916,"income":36627.0},{"client_id":8017,"income":51111.0},{"client_id":5830,"income":86857.0},{"client_id":4597,"income":82072.0},{"client_id":7023,"income":46231.0},{"client_id":8086,"income":42243.0},{"client_id":8825,"income":51195.0},{"client_id":2930,"income":68092.0},{"client_id":1928,"income":31814.0},{"client_id":7108,"income":51390.0},{"client_id":10925,"income":76630.0},{"client_id":9960,"income":26868.0},{"client_id":8800,"income":48948.0},{"client_id":9224,"income":55260.0},{"client_id":5519,"income":64090.0},{"client_id":5046,"income":78331.0},{"client_id":7037,"income":37087.0},{"client_id":905,"income":21846.0},{"client_id":8624,"income":81320.0},{"client_id":8945,"income":54137.0},{"client_id":6445,"income":66825.0},{"client_id":2727,"income":57100.0},{"client_id":6404,"income":58917.0},{"client_id":11074,"income":85072.0},{"client_id":10150,"income":86429.0},{"client_id":1968,"income":45684.0},{"client_id":6534,"income":47889.0},{"client_id":9485,"income":45921.0},{"client_id":7053,"income":78420.0},{"client_id":4654,"income":75114.0},{"client_id":9760,"income":52278.0},{"client_id":1048,"income":35641.0},{"client_id":10619,"income":95529.0},{"client_id":9308,"income":62820.0},{"client_id":10505,"income":73113.0},{"client_id":8362,"income":84169.0},{"client_id":2625,"income":42607.0},{"client_id":4637,"income":74637.0},{"client_id":9972,"income":46015.0},{"client_id":4483,"income":72354.0},{"client_id":4487,"income":39858.0},{"client_id":4988,"income":34469.0},{"client_id":8931,"income":83033.0},{"client_id":5871,"income":24401.0},{"client_id":2008,"income":77583.0},{"client_id":3139,"income":74116.0},{"client_id":10037,"income":74293.0},{"client_id":10673,"income":68397.0},{"client_id":5303,"income":79632.0},{"client_id":538,"income":46107.0},{"client_id":7922,"income":64950.0},{"client_id":5692,"income":25443.0},{"client_id":4843,"income":75127.0},{"client_id":6383,"income":32892.0},{"client_id":1628,"income":71796.0},{"client_id":1204,"income":67536.0},{"client_id":3673,"income":55239.0},{"client_id":760,"income":60554.0},{"client_id":8957,"income":64831.0},{"client_id":4128,"income":56067.0},{"client_id":6810,"income":82025.0},{"client_id":5386,"income":94384.0},{"client_id":8700,"income":14906.0},{"client_id":3202,"income":51563.0},{"client_id":1328,"income":57937.0},{"client_id":8405,"income":68274.0},{"client_id":6515,"income":39771.0},{"client_id":2882,"income":67893.0},{"client_id":7574,"income":27922.0},{"client_id":6387,"income":52190.0},{"client_id":5320,"income":44051.0},{"client_id":5048,"income":42767.0},{"client_id":8146,"income":46106.0},{"client_id":10031,"income":16927.0},{"client_id":5748,"income":59754.0},{"client_id":2134,"income":53700.0},{"client_id":1523,"income":59041.0},{"client_id":9665,"income":54237.0},{"client_id":4640,"income":70647.0},{"client_id":3635,"income":52597.0},{"client_id":3547,"income":41021.0},{"client_id":2456,"income":40233.0},{"client_id":5633,"income":50183.0},{"client_id":7801,"income":54753.0},{"client_id":10489,"income":92955.0},{"client_id":7011,"income":33471.0},{"client_id":2620,"income":34596.0},{"client_id":3933,"income":44010.0},{"client_id":10981,"income":84219.0},{"client_id":1734,"income":40706.0},{"client_id":10995,"income":15716.0},{"client_id":6357,"income":59052.0},{"client_id":9209,"income":80573.0},{"client_id":10286,"income":83715.0},{"client_id":2611,"income":82576.0},{"client_id":1600,"income":56962.0},{"client_id":3308,"income":35704.0},{"client_id":5407,"income":53103.0},{"client_id":2166,"income":46779.0},{"client_id":3955,"income":4861.0},{"client_id":6634,"income":33462.0},{"client_id":3056,"income":63693.0},{"client_id":5718,"income":80763.0},{"client_id":6872,"income":65352.0},{"client_id":8164,"income":82170.0},{"client_id":4580,"income":75759.0},{"client_id":9305,"income":79689.0},{"client_id":453,"income":35340.0},{"client_id":8545,"income":85683.0},{"client_id":9850,"income":24884.0},{"client_id":7378,"income":42021.0},{"client_id":7646,"income":64449.0},{"client_id":1640,"income":64587.0},{"client_id":5184,"income":34824.0},{"client_id":8492,"income":75437.0},{"client_id":11188,"income":26091.0},{"client_id":1212,"income":52845.0},{"client_id":9097,"income":46086.0},{"client_id":10473,"income":78028.0},{"client_id":7962,"income":95169.0},{"client_id":9984,"income":56337.0},{"client_id":5527,"income":22434.0},{"client_id":6374,"income":36930.0},{"client_id":7453,"income":36130.0},{"client_id":8952,"income":65569.0},{"client_id":241,"income":83844.0},{"client_id":8975,"income":19514.0},{"client_id":6119,"income":36736.0},{"client_id":5236,"income":77568.0},{"client_id":5723,"income":49187.0},{"client_id":1710,"income":30168.0},{"client_id":1970,"income":34053.0},{"client_id":5313,"income":38196.0},{"client_id":10634,"income":59412.0},{"client_id":7010,"income":70924.0},{"client_id":8562,"income":54165.0},{"client_id":3158,"income":32300.0},{"client_id":4436,"income":20180.0},{"client_id":5287,"income":34961.0},{"client_id":2445,"income":28440.0},{"client_id":6059,"income":64504.0},{"client_id":4550,"income":33564.0},{"client_id":4240,"income":17345.0},{"client_id":8911,"income":56320.0},{"client_id":3706,"income":28647.0},{"client_id":3628,"income":15038.0},{"client_id":10175,"income":32173.0},{"client_id":8985,"income":68316.0},{"client_id":5204,"income":74538.0},{"client_id":9220,"income":91700.0},{"client_id":9888,"income":68695.0},{"client_id":5263,"income":31056.0},{"client_id":1020,"income":79593.0},{"client_id":9503,"income":28071.0},{"client_id":10613,"income":37334.0},{"client_id":67,"income":46423.0},{"client_id":6019,"income":37126.0},{"client_id":5863,"income":47703.0},{"client_id":3717,"income":61180.0},{"client_id":6730,"income":38998.0},{"client_id":10749,"income":8028.0},{"client_id":4998,"income":76081.0},{"client_id":6287,"income":34728.0},{"client_id":5985,"income":33168.0},{"client_id":4754,"income":33585.0},{"client_id":4002,"income":77037.0},{"client_id":8870,"income":35196.0},{"client_id":966,"income":44529.0},{"client_id":4767,"income":70924.0},{"client_id":9725,"income":28764.0},{"client_id":4475,"income":69098.0},{"client_id":5740,"income":25959.0},{"client_id":5731,"income":27100.0},{"client_id":7290,"income":70596.0},{"client_id":3846,"income":42557.0},{"client_id":8104,"income":53312.0},{"client_id":4507,"income":72228.0},{"client_id":11013,"income":67605.0},{"client_id":4491,"income":62845.0},{"client_id":3759,"income":65196.0},{"client_id":1162,"income":42000.0},{"client_id":2055,"income":35860.0},{"client_id":10766,"income":65526.0},{"client_id":4415,"income":16860.0},{"client_id":3005,"income":83528.0},{"client_id":2223,"income":64176.0},{"client_id":4817,"income":22304.0},{"client_id":2875,"income":67023.0},{"client_id":10536,"income":32892.0},{"client_id":11112,"income":70713.0},{"client_id":3807,"income":59925.0},{"client_id":9197,"income":39722.0},{"client_id":10832,"income":46610.0},{"client_id":6421,"income":88347.0},{"client_id":4207,"income":87171.0},{"client_id":577,"income":26907.0},{"client_id":10855,"income":50014.0},{"client_id":3081,"income":41014.0},{"client_id":3535,"income":66294.0},{"client_id":247,"income":36715.0},{"client_id":8707,"income":79456.0},{"client_id":9523,"income":40479.0},{"client_id":6072,"income":75345.0},{"client_id":6295,"income":54233.0},{"client_id":10914,"income":24163.0},{"client_id":1509,"income":84460.0},{"client_id":5577,"income":43776.0},{"client_id":7348,"income":71691.0},{"client_id":1127,"income":85844.0},{"client_id":1833,"income":39190.0},{"client_id":4944,"income":71367.0},{"client_id":9080,"income":38578.0},{"client_id":6466,"income":57236.0},{"client_id":9964,"income":61825.0},{"client_id":4790,"income":79803.0},{"client_id":10245,"income":80910.0},{"client_id":1109,"income":27590.0},{"client_id":6001,"income":56775.0},{"client_id":5538,"income":83829.0},{"client_id":10552,"income":54210.0},{"client_id":1545,"income":38508.0},{"client_id":7409,"income":53187.0},{"client_id":4444,"income":30023.0},{"client_id":146,"income":76045.0},{"client_id":6271,"income":50870.0},{"client_id":10065,"income":15315.0},{"client_id":4741,"income":65463.0},{"client_id":246,"income":66480.0},{"client_id":375,"income":76773.0},{"client_id":1524,"income":81698.0},{"client_id":10022,"income":54466.0},{"client_id":7451,"income":98777.0},{"client_id":11010,"income":16269.0},{"client_id":4356,"income":71819.0},{"client_id":3885,"income":33569.0},{"client_id":1175,"income":36262.0},{"client_id":880,"income":22634.0},{"client_id":2320,"income":47025.0},{"client_id":850,"income":70566.0},{"client_id":4713,"income":31605.0},{"client_id":675,"income":52034.0},{"client_id":5025,"income":48526.0},{"client_id":2308,"income":46734.0},{"client_id":5995,"income":39552.0},{"client_id":6749,"income":86358.0},{"client_id":1010,"income":46931.0},{"client_id":8977,"income":16581.0},{"client_id":4756,"income":63998.0},{"client_id":3412,"income":67381.0},{"client_id":606,"income":25930.0},{"client_id":5961,"income":42693.0},{"client_id":2975,"income":85606.0},{"client_id":2894,"income":72903.0},{"client_id":7613,"income":49669.0},{"client_id":10542,"income":36778.0},{"client_id":8015,"income":85696.0},{"client_id":10617,"income":10979.0},{"client_id":11166,"income":49678.0},{"client_id":849,"income":56129.0},{"client_id":523,"income":37155.0},{"client_id":4066,"income":21282.0},{"client_id":8414,"income":33419.0},{"client_id":819,"income":63285.0},{"client_id":4961,"income":21255.0},{"client_id":749,"income":42162.0},{"client_id":5430,"income":54450.0},{"client_id":7755,"income":57744.0},{"client_id":10525,"income":26576.0},{"client_id":1453,"income":57513.0},{"client_id":8310,"income":68142.0},{"client_id":10710,"income":7500.0},{"client_id":5031,"income":83145.0},{"client_id":2613,"income":54197.0},{"client_id":213,"income":23091.0},{"client_id":967,"income":46049.0},{"client_id":1077,"income":56715.0},{"client_id":7959,"income":79410.0},{"client_id":640,"income":57304.0},{"client_id":4252,"income":44375.0},{"client_id":8432,"income":54450.0},{"client_id":6218,"income":59594.0},{"client_id":6905,"income":80685.0},{"client_id":5922,"income":40344.0},{"client_id":3598,"income":62710.0},{"client_id":6116,"income":48985.0},{"client_id":6263,"income":35322.0},{"client_id":10486,"income":77142.0},{"client_id":2410,"income":81657.0},{"client_id":193,"income":14421.0},{"client_id":3363,"income":20130.0},{"client_id":8278,"income":74214.0},{"client_id":10660,"income":66726.0},{"client_id":8686,"income":23724.0},{"client_id":1604,"income":47353.0},{"client_id":5907,"income":33444.0},{"client_id":10669,"income":54386.0},{"client_id":2918,"income":28510.0},{"client_id":5735,"income":90638.0},{"client_id":359,"income":48070.0},{"client_id":8387,"income":43140.0},{"client_id":1829,"income":54959.0},{"client_id":3839,"income":15056.0},{"client_id":9392,"income":26954.0},{"client_id":2292,"income":22327.0},{"client_id":10466,"income":44393.0},{"client_id":9855,"income":62000.0},{"client_id":4088,"income":31497.0},{"client_id":5231,"income":45894.0},{"client_id":590,"income":78579.0},{"client_id":8732,"income":67369.0},{"client_id":2315,"income":58401.0},{"client_id":3515,"income":62307.0},{"client_id":2245,"income":43641.0},{"client_id":6283,"income":63841.0},{"client_id":2246,"income":46891.0},{"client_id":6606,"income":70091.0},{"client_id":5545,"income":78075.0},{"client_id":7342,"income":59184.0},{"client_id":837,"income":54809.0},{"client_id":9500,"income":58113.0},{"client_id":3602,"income":51412.0},{"client_id":234,"income":15287.0},{"client_id":2995,"income":66636.0},{"client_id":1118,"income":50965.0},{"client_id":7789,"income":84618.0},{"client_id":3068,"income":18351.0},{"client_id":8955,"income":40451.0},{"client_id":945,"income":36317.0},{"client_id":5644,"income":42213.0},{"client_id":7192,"income":65748.0},{"client_id":2324,"income":77044.0},{"client_id":697,"income":74918.0},{"client_id":3439,"income":56721.0},{"client_id":1506,"income":42160.0},{"client_id":232,"income":61559.0},{"client_id":8876,"income":33629.0},{"client_id":4500,"income":68682.0},{"client_id":9739,"income":34377.0},{"client_id":10395,"income":8940.0},{"client_id":1176,"income":26228.0},{"client_id":1627,"income":77297.0},{"client_id":938,"income":40211.0},{"client_id":2740,"income":33438.0},{"client_id":257,"income":75032.0},{"client_id":4058,"income":61284.0},{"client_id":7736,"income":22518.0},{"client_id":8210,"income":54730.0},{"client_id":833,"income":38452.0},{"client_id":6230,"income":44421.0},{"client_id":7325,"income":38197.0},{"client_id":1307,"income":41986.0},{"client_id":1502,"income":28427.0},{"client_id":6211,"income":37395.0},{"client_id":843,"income":64722.0},{"client_id":4174,"income":55249.0},{"client_id":9757,"income":84906.0},{"client_id":6918,"income":28691.0},{"client_id":286,"income":44213.0},{"client_id":11086,"income":25707.0},{"client_id":1921,"income":59062.0},{"client_id":4138,"income":76624.0},{"client_id":7718,"income":66000.0},{"client_id":1291,"income":27683.0},{"client_id":6862,"income":1730.0},{"client_id":4136,"income":7500.0},{"client_id":803,"income":40521.0},{"client_id":4298,"income":20427.0},{"client_id":10833,"income":65106.0},{"client_id":9606,"income":69969.0},{"client_id":8534,"income":67433.0},{"client_id":5153,"income":77766.0},{"client_id":961,"income":74716.0},{"client_id":5011,"income":68118.0},{"client_id":6653,"income":55158.0},{"client_id":9094,"income":62972.0},{"client_id":810,"income":74190.0},{"client_id":5493,"income":39356.0},{"client_id":2147,"income":76653.0},{"client_id":5107,"income":35860.0},{"client_id":3979,"income":90687.0},{"client_id":6049,"income":73450.0},{"client_id":8147,"income":31454.0},{"client_id":1857,"income":47139.0},{"client_id":3910,"income":83829.0},{"client_id":5207,"income":53378.0},{"client_id":11114,"income":19656.0},{"client_id":5429,"income":45579.0},{"client_id":9400,"income":85485.0},{"client_id":1740,"income":55956.0},{"client_id":7488,"income":64191.0},{"client_id":195,"income":38808.0},{"client_id":635,"income":57183.0},{"client_id":7527,"income":23748.0},{"client_id":10319,"income":66303.0},{"client_id":2296,"income":37368.0},{"client_id":10637,"income":40800.0},{"client_id":2931,"income":71847.0},{"client_id":907,"income":46149.0},{"client_id":3698,"income":78687.0},{"client_id":9516,"income":49118.0},{"client_id":679,"income":37633.0},{"client_id":7384,"income":39767.0},{"client_id":5043,"income":26997.0},{"client_id":5267,"income":33986.0},{"client_id":339,"income":57091.0},{"client_id":2516,"income":46831.0},{"client_id":9010,"income":83151.0},{"client_id":378,"income":52531.0},{"client_id":4808,"income":15759.0},{"client_id":5068,"income":22804.0},{"client_id":7628,"income":43050.0},{"client_id":7128,"income":42997.0},{"client_id":2811,"income":48918.0},{"client_id":3551,"income":60033.0},{"client_id":1663,"income":34043.0},{"client_id":5543,"income":57811.0},{"client_id":1577,"income":78569.0},{"client_id":10641,"income":7500.0},{"client_id":5336,"income":157733.0},{"client_id":6024,"income":94384.0},{"client_id":1878,"income":23148.0},{"client_id":3099,"income":44267.0},{"client_id":6055,"income":71626.0},{"client_id":5841,"income":60894.0},{"client_id":3972,"income":50200.0},{"client_id":4394,"income":81051.0},{"client_id":5758,"income":65169.0},{"client_id":6658,"income":59868.0},{"client_id":4603,"income":65695.0},{"client_id":8427,"income":64857.0},{"client_id":10260,"income":45143.0},{"client_id":7143,"income":74805.0},{"client_id":8789,"income":59060.0},{"client_id":6197,"income":27238.0},{"client_id":4554,"income":47009.0},{"client_id":4937,"income":46094.0},{"client_id":1920,"income":40321.0},{"client_id":8749,"income":37235.0},{"client_id":1650,"income":81843.0},{"client_id":10377,"income":46692.0},{"client_id":9206,"income":77382.0},{"client_id":10971,"income":37774.0},{"client_id":6398,"income":18393.0},{"client_id":9212,"income":72828.0},{"client_id":7937,"income":24711.0},{"client_id":839,"income":45503.0},{"client_id":4246,"income":6560.0},{"client_id":158,"income":71604.0},{"client_id":4832,"income":27244.0},{"client_id":5621,"income":48752.0},{"client_id":1945,"income":71434.0},{"client_id":5147,"income":90842.0},{"client_id":2535,"income":88097.0},{"client_id":11039,"income":51948.0},{"client_id":9495,"income":71853.0},{"client_id":9635,"income":35876.0},{"client_id":2173,"income":40049.0},{"client_id":942,"income":39660.0},{"client_id":9386,"income":50127.0},{"client_id":5510,"income":43263.0},{"client_id":873,"income":62845.0},{"client_id":2253,"income":18929.0},{"client_id":5181,"income":24367.0},{"client_id":979,"income":33249.0},{"client_id":10390,"income":26887.0},{"client_id":4698,"income":50150.0},{"client_id":7793,"income":62061.0},{"client_id":1745,"income":85696.0},{"client_id":10590,"income":76542.0},{"client_id":5080,"income":70515.0},{"client_id":8369,"income":18227.0},{"client_id":5232,"income":69139.0},{"client_id":2407,"income":69109.0},{"client_id":3834,"income":69627.0},{"client_id":7912,"income":38136.0},{"client_id":7712,"income":62159.0},{"client_id":1065,"income":80695.0},{"client_id":7275,"income":33316.0},{"client_id":1343,"income":58554.0},{"client_id":1384,"income":17256.0},{"client_id":9967,"income":53034.0},{"client_id":6181,"income":52203.0},{"client_id":10507,"income":59601.0},{"client_id":2674,"income":75154.0},{"client_id":2698,"income":47025.0},{"client_id":3231,"income":37971.0},{"client_id":4096,"income":41335.0},{"client_id":10476,"income":67267.0},{"client_id":5948,"income":57338.0},{"client_id":9140,"income":50523.0},{"client_id":10258,"income":35791.0},{"client_id":5675,"income":50611.0},{"client_id":4743,"income":56242.0},{"client_id":8805,"income":48904.0},{"client_id":1542,"income":56243.0},{"client_id":6770,"income":21355.0},{"client_id":8773,"income":57420.0},{"client_id":10475,"income":null},{"client_id":10420,"income":46390.0},{"client_id":7514,"income":54342.0},{"client_id":2902,"income":null},{"client_id":4345,"income":null},{"client_id":793,"income":20895.0},{"client_id":10909,"income":92344.0},{"client_id":3769,"income":null},{"client_id":8702,"income":26907.0},{"client_id":4791,"income":44964.0},{"client_id":2963,"income":75507.0},{"client_id":8216,"income":53761.0},{"client_id":8140,"income":22682.0},{"client_id":10146,"income":38887.0},{"client_id":5289,"income":41658.0},{"client_id":2587,"income":29791.0},{"client_id":4405,"income":63915.0},{"client_id":8663,"income":39996.0},{"client_id":2589,"income":26759.0},{"client_id":3421,"income":63841.0},{"client_id":10490,"income":51039.0},{"client_id":4094,"income":60544.0},{"client_id":9958,"income":65685.0},{"client_id":2534,"income":37716.0},{"client_id":4188,"income":36864.0},{"client_id":6613,"income":44511.0},{"client_id":10827,"income":36947.0},{"client_id":5491,"income":47352.0},{"client_id":8402,"income":67087.0},{"client_id":8783,"income":57045.0},{"client_id":10010,"income":36957.0},{"client_id":618,"income":69389.0},{"client_id":9121,"income":80134.0},{"client_id":361,"income":43142.0},{"client_id":4310,"income":80589.0},{"client_id":2678,"income":34412.0},{"client_id":6376,"income":57537.0},{"client_id":524,"income":22634.0},{"client_id":10341,"income":51315.0},{"client_id":5654,"income":36026.0},{"client_id":4098,"income":24639.0},{"client_id":5824,"income":34578.0},{"client_id":7000,"income":65704.0},{"client_id":2561,"income":63810.0},{"client_id":5229,"income":54132.0},{"client_id":4086,"income":18690.0},{"client_id":2428,"income":28164.0},{"client_id":8254,"income":34596.0},{"client_id":2836,"income":43269.0},{"client_id":8418,"income":38741.0},{"client_id":1362,"income":31907.0},{"client_id":7152,"income":27100.0},{"client_id":10033,"income":31163.0},{"client_id":9349,"income":92533.0},{"client_id":274,"income":34853.0},{"client_id":3388,"income":70844.0},{"client_id":922,"income":31086.0},{"client_id":8588,"income":60544.0},{"client_id":2518,"income":20491.0},{"client_id":574,"income":42523.0},{"client_id":3220,"income":39922.0},{"client_id":5967,"income":33402.0},{"client_id":1183,"income":36408.0},{"client_id":6856,"income":21645.0},{"client_id":4530,"income":78427.0},{"client_id":1553,"income":82657.0},{"client_id":4682,"income":51876.0},{"client_id":8204,"income":78041.0},{"client_id":5221,"income":52852.0},{"client_id":1232,"income":70038.0},{"client_id":1927,"income":69401.0},{"client_id":5788,"income":46053.0},{"client_id":6652,"income":77343.0},{"client_id":6246,"income":73892.0},{"client_id":5975,"income":40304.0},{"client_id":6875,"income":32727.0},{"client_id":4399,"income":68695.0},{"client_id":4042,"income":43300.0},{"client_id":2157,"income":26290.0},{"client_id":10133,"income":93790.0},{"client_id":2525,"income":38410.0},{"client_id":8233,"income":64866.0},{"client_id":9483,"income":57957.0},{"client_id":2945,"income":46015.0},{"client_id":10403,"income":16531.0},{"client_id":5074,"income":28072.0},{"client_id":10524,"income":49476.0},{"client_id":4690,"income":50725.0},{"client_id":7521,"income":83844.0},{"client_id":7196,"income":41145.0},{"client_id":4406,"income":67419.0},{"client_id":9672,"income":23162.0},{"client_id":4864,"income":34380.0},{"client_id":4706,"income":34704.0},{"client_id":4070,"income":94871.0},{"client_id":25,"income":65148.0},{"client_id":3697,"income":39898.0},{"client_id":217,"income":64857.0},{"client_id":4220,"income":59892.0},{"client_id":5286,"income":41020.0},{"client_id":9559,"income":57072.0},{"client_id":2849,"income":60474.0},{"client_id":7787,"income":62807.0},{"client_id":3102,"income":19414.0},{"client_id":5868,"income":19107.0},{"client_id":8370,"income":75484.0},{"client_id":9988,"income":70379.0},{"client_id":2939,"income":79419.0},{"client_id":5529,"income":64014.0},{"client_id":9743,"income":76998.0},{"client_id":5763,"income":49854.0},{"client_id":3478,"income":60585.0},{"client_id":7494,"income":42873.0},{"client_id":1763,"income":87679.0},{"client_id":7250,"income":57867.0},{"client_id":2005,"income":35765.0},{"client_id":10770,"income":65492.0},{"client_id":6885,"income":32952.0},{"client_id":2072,"income":53374.0},{"client_id":9463,"income":71706.0},{"client_id":6318,"income":68487.0},{"client_id":4093,"income":53253.0},{"client_id":5751,"income":31163.0},{"client_id":3340,"income":42014.0},{"client_id":3594,"income":54108.0},{"client_id":3584,"income":49667.0},{"client_id":3643,"income":63206.0},{"client_id":851,"income":57136.0},{"client_id":7706,"income":46772.0},{"client_id":3967,"income":78931.0},{"client_id":10128,"income":53977.0},{"client_id":486,"income":84219.0},{"client_id":9,"income":46098.0},{"client_id":9451,"income":73538.0},{"client_id":9264,"income":79529.0},{"client_id":3865,"income":20981.0},{"client_id":2853,"income":51766.0},{"client_id":1490,"income":55759.0},{"client_id":6310,"income":33039.0},{"client_id":10380,"income":37787.0},{"client_id":3887,"income":27242.0},{"client_id":4278,"income":87188.0},{"client_id":8643,"income":69930.0},{"client_id":1998,"income":37697.0},{"client_id":10795,"income":37401.0},{"client_id":11110,"income":3502.0},{"client_id":2408,"income":58597.0},{"client_id":202,"income":82032.0},{"client_id":7998,"income":28087.0},{"client_id":830,"income":74004.0},{"client_id":3536,"income":19740.0},{"client_id":6050,"income":57036.0},{"client_id":125,"income":53083.0},{"client_id":3463,"income":69283.0},{"client_id":2804,"income":46098.0},{"client_id":3745,"income":23331.0},{"client_id":9771,"income":23331.0},{"client_id":451,"income":9255.0},{"client_id":10530,"income":67786.0},{"client_id":1079,"income":71969.0},{"client_id":8920,"income":59235.0},{"client_id":6678,"income":31928.0},{"client_id":3852,"income":74881.0},{"client_id":528,"income":65819.0},{"client_id":73,"income":51411.0},{"client_id":5589,"income":51983.0},{"client_id":10212,"income":42386.0},{"client_id":6365,"income":30390.0},{"client_id":5636,"income":30983.0},{"client_id":591,"income":66033.0},{"client_id":2217,"income":37284.0},{"client_id":2544,"income":57530.0},{"client_id":7725,"income":76800.0},{"client_id":8091,"income":63943.0},{"client_id":7321,"income":76081.0},{"client_id":5462,"income":67445.0},{"client_id":7791,"income":37054.0},{"client_id":955,"income":47175.0},{"client_id":4037,"income":31859.0},{"client_id":6642,"income":27215.0},{"client_id":2793,"income":70179.0},{"client_id":5424,"income":39922.0},{"client_id":879,"income":49681.0},{"client_id":9530,"income":24645.0},{"client_id":4828,"income":79865.0},{"client_id":10699,"income":44322.0},{"client_id":1497,"income":47958.0},{"client_id":7476,"income":63972.0},{"client_id":4390,"income":75315.0},{"client_id":10478,"income":55517.0},{"client_id":1081,"income":75283.0},{"client_id":4261,"income":82800.0},{"client_id":9916,"income":38998.0},{"client_id":5350,"income":90638.0},{"client_id":8135,"income":27161.0},{"client_id":8685,"income":42014.0},{"client_id":4967,"income":38201.0},{"client_id":2130,"income":45203.0},{"client_id":9298,"income":81574.0},{"client_id":8175,"income":34935.0},{"client_id":6257,"income":60482.0},{"client_id":3790,"income":34633.0},{"client_id":9952,"income":78093.0},{"client_id":3503,"income":82460.0},{"client_id":5223,"income":45903.0},{"client_id":4608,"income":81361.0},{"client_id":1626,"income":35860.0},{"client_id":4764,"income":40442.0},{"client_id":2471,"income":61482.0},{"client_id":5892,"income":34968.0},{"client_id":2612,"income":75794.0},{"client_id":4971,"income":31497.0},{"client_id":5185,"income":74268.0},{"client_id":10069,"income":13724.0},{"client_id":2262,"income":45143.0},{"client_id":1131,"income":52569.0},{"client_id":1041,"income":48432.0},{"client_id":24,"income":17144.0},{"client_id":3409,"income":36108.0},{"client_id":7022,"income":76445.0},{"client_id":7943,"income":36663.0},{"client_id":5272,"income":53843.0},{"client_id":5453,"income":90226.0},{"client_id":2565,"income":70638.0},{"client_id":800,"income":44512.0},{"client_id":11092,"income":27116.0},{"client_id":5062,"income":54072.0},{"client_id":8969,"income":71855.0},{"client_id":4656,"income":51250.0},{"client_id":4480,"income":60432.0},{"client_id":9971,"income":65526.0},{"client_id":6729,"income":68655.0},{"client_id":1773,"income":12393.0},{"client_id":9242,"income":64509.0},{"client_id":1764,"income":33955.0},{"client_id":6215,"income":31353.0},{"client_id":10099,"income":55434.0},{"client_id":5423,"income":28359.0},{"client_id":940,"income":57100.0},{"client_id":3011,"income":69139.0},{"client_id":3298,"income":52973.0},{"client_id":8286,"income":51717.0},{"client_id":9668,"income":18793.0},{"client_id":5120,"income":66664.0},{"client_id":6097,"income":50664.0},{"client_id":7019,"income":54414.0},{"client_id":7408,"income":54549.0},{"client_id":8041,"income":47111.0},{"client_id":252,"income":41003.0},{"client_id":9986,"income":19444.0},{"client_id":3276,"income":36301.0},{"client_id":3859,"income":73059.0},{"client_id":3570,"income":42731.0},{"client_id":3783,"income":52854.0},{"client_id":10207,"income":22775.0},{"client_id":10906,"income":46681.0},{"client_id":3427,"income":59821.0},{"client_id":5209,"income":50002.0},{"client_id":10711,"income":69755.0},{"client_id":10785,"income":44078.0},{"client_id":2814,"income":30560.0},{"client_id":6866,"income":35924.0},{"client_id":1665,"income":64140.0},{"client_id":6575,"income":56386.0},{"client_id":3829,"income":24594.0},{"client_id":3091,"income":75774.0},{"client_id":10141,"income":39228.0},{"client_id":5177,"income":58494.0},{"client_id":7005,"income":58684.0},{"client_id":6409,"income":57136.0},{"client_id":7485,"income":56551.0},{"client_id":8079,"income":22448.0},{"client_id":8395,"income":82014.0},{"client_id":10352,"income":34213.0},{"client_id":4931,"income":157146.0},{"client_id":13,"income":25358.0},{"client_id":1834,"income":35544.0},{"client_id":2285,"income":36634.0},{"client_id":2295,"income":62670.0},{"client_id":1378,"income":50334.0},{"client_id":2781,"income":72066.0},{"client_id":1165,"income":50729.0},{"client_id":1404,"income":34916.0},{"client_id":6457,"income":64892.0},{"client_id":2639,"income":43602.0},{"client_id":8299,"income":33996.0},{"client_id":6437,"income":41473.0},{"client_id":6912,"income":63246.0},{"client_id":7327,"income":36732.0},{"client_id":5299,"income":69084.0},{"client_id":4127,"income":77766.0},{"client_id":8143,"income":37929.0},{"client_id":1964,"income":86610.0},{"client_id":3690,"income":80141.0},{"client_id":3433,"income":72635.0},{"client_id":3389,"income":69016.0},{"client_id":4712,"income":20193.0},{"client_id":1170,"income":27573.0},{"client_id":6347,"income":15862.0},{"client_id":4065,"income":49544.0},{"client_id":8230,"income":33228.0},{"client_id":1215,"income":70440.0},{"client_id":5939,"income":38232.0},{"client_id":2156,"income":22554.0},{"client_id":7788,"income":23536.0},{"client_id":10323,"income":49413.0},{"client_id":7947,"income":42231.0},{"client_id":1891,"income":78789.0},{"client_id":2570,"income":56534.0},{"client_id":9256,"income":58350.0},{"client_id":295,"income":81217.0},{"client_id":7397,"income":49090.0},{"client_id":6349,"income":61787.0},{"client_id":10790,"income":18169.0},{"client_id":10398,"income":24336.0},{"client_id":2431,"income":18222.0},{"client_id":550,"income":62335.0},{"client_id":1890,"income":42033.0},{"client_id":10742,"income":86580.0},{"client_id":10356,"income":41437.0},{"client_id":4676,"income":73705.0},{"client_id":8852,"income":61064.0},{"client_id":3565,"income":38452.0},{"client_id":5294,"income":18358.0},{"client_id":1958,"income":55012.0},{"client_id":7349,"income":9722.0},{"client_id":8799,"income":38175.0},{"client_id":1351,"income":58656.0},{"client_id":1045,"income":52117.0},{"client_id":7732,"income":64813.0},{"client_id":8070,"income":54222.0},{"client_id":477,"income":83512.0},{"client_id":7832,"income":77520.0},{"client_id":2202,"income":41154.0},{"client_id":7396,"income":80398.0},{"client_id":4055,"income":18746.0},{"client_id":10340,"income":35196.0},{"client_id":10091,"income":60230.0},{"client_id":7629,"income":22108.0},{"client_id":10640,"income":44392.0},{"client_id":3498,"income":55424.0},{"client_id":6742,"income":17688.0},{"client_id":1172,"income":92491.0},{"client_id":569,"income":90273.0},{"client_id":4686,"income":82571.0},{"client_id":1381,"income":38513.0},{"client_id":2634,"income":16653.0},{"client_id":10905,"income":42586.0},{"client_id":1744,"income":23529.0},{"client_id":1000,"income":74881.0},{"client_id":3828,"income":71107.0},{"client_id":8605,"income":46910.0},{"client_id":10304,"income":18690.0},{"client_id":4351,"income":37244.0},{"client_id":10129,"income":82427.0},{"client_id":2499,"income":75342.0},{"client_id":10092,"income":70044.0},{"client_id":7500,"income":79146.0},{"client_id":5796,"income":77437.0},{"client_id":10556,"income":54984.0},{"client_id":1064,"income":42403.0},{"client_id":48,"income":55761.0},{"client_id":7610,"income":37292.0},{"client_id":263,"income":45576.0},{"client_id":10814,"income":70321.0},{"client_id":9710,"income":58086.0},{"client_id":9292,"income":81795.0},{"client_id":10250,"income":28389.0},{"client_id":7881,"income":66835.0},{"client_id":5847,"income":69901.0},{"client_id":737,"income":80360.0},{"client_id":3571,"income":63342.0},{"client_id":7807,"income":44989.0},{"client_id":3878,"income":31859.0},{"client_id":5092,"income":51569.0},{"client_id":2154,"income":30372.0},{"client_id":5394,"income":16014.0},{"client_id":3798,"income":41120.0},{"client_id":3524,"income":39763.0},{"client_id":5247,"income":38725.0},{"client_id":5883,"income":77981.0},{"client_id":2118,"income":62905.0},{"client_id":8812,"income":13533.0},{"client_id":6616,"income":59481.0},{"client_id":2797,"income":72117.0},{"client_id":4328,"income":21955.0},{"client_id":9167,"income":67131.0},{"client_id":10560,"income":36802.0},{"client_id":2631,"income":71853.0},{"client_id":8312,"income":28249.0},{"client_id":5534,"income":47808.0},{"client_id":5093,"income":25509.0},{"client_id":7592,"income":51012.0},{"client_id":8895,"income":70596.0},{"client_id":8584,"income":85431.0},{"client_id":2694,"income":42664.0},{"client_id":8910,"income":42586.0},{"client_id":7433,"income":29760.0},{"client_id":164,"income":28973.0},{"client_id":10477,"income":39435.0},{"client_id":2681,"income":65370.0},{"client_id":5150,"income":20194.0},{"client_id":5283,"income":42473.0},{"client_id":9645,"income":64590.0},{"client_id":10678,"income":71232.0},{"client_id":7261,"income":34600.0},{"client_id":9648,"income":46904.0},{"client_id":2870,"income":49094.0},{"client_id":8008,"income":36075.0},{"client_id":1513,"income":60839.0},{"client_id":6173,"income":77298.0},{"client_id":1419,"income":34026.0},{"client_id":9150,"income":48918.0},{"client_id":7960,"income":82122.0},{"client_id":1250,"income":37697.0},{"client_id":9905,"income":34074.0},{"client_id":10691,"income":28520.0},{"client_id":7002,"income":62535.0},{"client_id":2952,"income":36273.0},{"client_id":8439,"income":63404.0},{"client_id":762,"income":75774.0},{"client_id":2831,"income":78416.0},{"client_id":6977,"income":75702.0},{"client_id":6289,"income":59385.0},{"client_id":4168,"income":37070.0},{"client_id":8397,"income":44689.0},{"client_id":9284,"income":53977.0},{"client_id":6237,"income":7144.0},{"client_id":3130,"income":18701.0},{"client_id":1619,"income":90369.0},{"client_id":1990,"income":63159.0},{"client_id":5513,"income":37758.0},{"client_id":269,"income":46757.0},{"client_id":8093,"income":79734.0},{"client_id":10513,"income":63207.0},{"client_id":10177,"income":72071.0},{"client_id":2549,"income":21840.0},{"client_id":5782,"income":58582.0},{"client_id":10057,"income":72282.0},{"client_id":10307,"income":50387.0},{"client_id":8566,"income":32583.0},{"client_id":2415,"income":62568.0},{"client_id":5684,"income":44635.0},{"client_id":8334,"income":33316.0},{"client_id":9166,"income":63967.0},{"client_id":1440,"income":52513.0},{"client_id":78,"income":25293.0},{"client_id":5441,"income":54111.0},{"client_id":5302,"income":78394.0},{"client_id":4687,"income":80739.0},{"client_id":1087,"income":22669.0},{"client_id":6859,"income":29236.0},{"client_id":9860,"income":44911.0},{"client_id":7129,"income":54693.0},{"client_id":5866,"income":48186.0},{"client_id":10521,"income":54809.0},{"client_id":7393,"income":41580.0},{"client_id":7849,"income":80336.0},{"client_id":332,"income":47743.0},{"client_id":9847,"income":62972.0},{"client_id":531,"income":57333.0},{"client_id":9576,"income":32313.0},{"client_id":6906,"income":84953.0},{"client_id":7419,"income":27071.0},{"client_id":3170,"income":68148.0},{"client_id":8527,"income":65735.0},{"client_id":7872,"income":86836.0},{"client_id":9931,"income":4023.0},{"client_id":10595,"income":30093.0},{"client_id":4609,"income":57705.0},{"client_id":5010,"income":25008.0},{"client_id":4427,"income":83257.0},{"client_id":11148,"income":22280.0},{"client_id":1168,"income":72159.0},{"client_id":9595,"income":64260.0},{"client_id":10163,"income":82733.0},{"client_id":2886,"income":74290.0},{"client_id":6710,"income":58217.0},{"client_id":5316,"income":21024.0},{"client_id":9029,"income":70116.0},{"client_id":521,"income":54006.0},{"client_id":1459,"income":69063.0},{"client_id":10241,"income":11448.0},{"client_id":1630,"income":61825.0},{"client_id":3254,"income":70886.0},{"client_id":9064,"income":69109.0},{"client_id":3678,"income":60208.0},{"client_id":4227,"income":32889.0},{"client_id":9467,"income":34738.0},{"client_id":8486,"income":30538.0},{"client_id":2186,"income":82326.0},{"client_id":3286,"income":26642.0},{"client_id":8602,"income":69932.0},{"client_id":3722,"income":44503.0},{"client_id":6715,"income":60200.0},{"client_id":4796,"income":49638.0},{"client_id":9612,"income":23830.0},{"client_id":3766,"income":33051.0},{"client_id":1399,"income":72905.0},{"client_id":1570,"income":69702.0},{"client_id":3426,"income":70300.0},{"client_id":3074,"income":70643.0},{"client_id":8341,"income":30396.0},{"client_id":5180,"income":50616.0},{"client_id":6461,"income":62772.0},{"client_id":7679,"income":30298.0},{"client_id":10702,"income":52413.0},{"client_id":7505,"income":44155.0},{"client_id":5113,"income":86979.0},{"client_id":10858,"income":76532.0},{"client_id":2961,"income":42081.0},{"client_id":2747,"income":67546.0},{"client_id":3010,"income":88420.0},{"client_id":5790,"income":31158.0},{"client_id":6892,"income":61671.0},{"client_id":1743,"income":69719.0},{"client_id":3578,"income":49160.0},{"client_id":8462,"income":24882.0},{"client_id":5558,"income":90933.0},{"client_id":4619,"income":113734.0},{"client_id":8780,"income":59292.0},{"client_id":10789,"income":45759.0},{"client_id":10779,"income":22148.0},{"client_id":5896,"income":73395.0},{"client_id":2337,"income":29819.0},{"client_id":10951,"income":45688.0},{"client_id":544,"income":62820.0},{"client_id":17,"income":60491.0},{"client_id":10680,"income":33235.0},{"client_id":3265,"income":35701.0},{"client_id":5623,"income":31535.0},{"client_id":5832,"income":92556.0},{"client_id":5544,"income":67384.0},{"client_id":6417,"income":80573.0},{"client_id":5831,"income":77870.0},{"client_id":7101,"income":52278.0},{"client_id":10176,"income":57107.0},{"client_id":2326,"income":18929.0},{"client_id":4385,"income":36038.0},{"client_id":2929,"income":20180.0},{"client_id":10686,"income":34230.0},{"client_id":2546,"income":31878.0},{"client_id":3283,"income":70932.0},{"client_id":3138,"income":91249.0},{"client_id":4994,"income":77598.0},{"client_id":7966,"income":80982.0},{"client_id":3112,"income":22701.0},{"client_id":10872,"income":55212.0},{"client_id":2181,"income":70617.0},{"client_id":1867,"income":64849.0},{"client_id":1518,"income":62694.0},{"client_id":5734,"income":61917.0},{"client_id":2878,"income":67472.0},{"client_id":1458,"income":21059.0},{"client_id":7007,"income":29543.0},{"client_id":6200,"income":75903.0},{"client_id":1403,"income":34984.0},{"client_id":4827,"income":54998.0},{"client_id":6250,"income":54356.0},{"client_id":9291,"income":34242.0},{"client_id":2478,"income":25410.0},{"client_id":1139,"income":73356.0},{"client_id":5138,"income":28320.0},{"client_id":5393,"income":23763.0},{"client_id":10413,"income":72570.0},{"client_id":5015,"income":34529.0},{"client_id":10868,"income":70792.0},{"client_id":10676,"income":63211.0},{"client_id":2495,"income":83891.0},{"client_id":7842,"income":36065.0},{"client_id":9955,"income":39898.0},{"client_id":6663,"income":51141.0},{"client_id":2162,"income":56939.0},{"client_id":3434,"income":80872.0},{"client_id":7919,"income":72335.0},{"client_id":5626,"income":61798.0},{"client_id":6428,"income":76842.0},{"client_id":8514,"income":29478.0},{"client_id":10448,"income":46998.0},{"client_id":2109,"income":96843.0},{"client_id":7530,"income":56551.0},{"client_id":8925,"income":70053.0},{"client_id":3009,"income":71670.0},{"client_id":6355,"income":44359.0},{"client_id":3517,"income":40887.0},{"client_id":1158,"income":48877.0},{"client_id":6203,"income":74485.0},{"client_id":7165,"income":64474.0},{"client_id":3595,"income":77226.0},{"client_id":8537,"income":72643.0},{"client_id":4331,"income":85738.0},{"client_id":6281,"income":55686.0},{"client_id":4338,"income":39062.0},{"client_id":2452,"income":34600.0},{"client_id":9507,"income":40794.0},{"client_id":8360,"income":54690.0},{"client_id":10311,"income":4428.0},{"client_id":5117,"income":32632.0},{"client_id":4867,"income":38236.0},{"client_id":9289,"income":36781.0},{"client_id":10913,"income":31385.0},{"client_id":3032,"income":24570.0},{"client_id":8524,"income":25509.0},{"client_id":3334,"income":94642.0},{"client_id":4470,"income":58646.0},{"client_id":1406,"income":53201.0},{"client_id":8619,"income":21994.0},{"client_id":10821,"income":57113.0},{"client_id":4552,"income":51373.0},{"client_id":898,"income":23477.0},{"client_id":9797,"income":58116.0},{"client_id":10949,"income":72968.0},{"client_id":8212,"income":39791.0},{"client_id":6248,"income":91712.0},{"client_id":10164,"income":94472.0},{"client_id":4547,"income":13672.0},{"client_id":6815,"income":96547.0},{"client_id":4122,"income":79205.0},{"client_id":10841,"income":56559.0},{"client_id":5370,"income":32644.0},{"client_id":176,"income":67506.0},{"client_id":4860,"income":24206.0},{"client_id":10757,"income":28420.0},{"client_id":4023,"income":22979.0},{"client_id":6679,"income":33279.0},{"client_id":9923,"income":46423.0},{"client_id":7181,"income":30368.0},{"client_id":3599,"income":63684.0},{"client_id":405,"income":41638.0},{"client_id":6870,"income":68805.0},{"client_id":832,"income":65814.0},{"client_id":2002,"income":71964.0},{"client_id":3657,"income":39146.0},{"client_id":500,"income":96876.0},{"client_id":1951,"income":34445.0},{"client_id":3262,"income":68281.0},{"client_id":4102,"income":37284.0},{"client_id":7042,"income":36790.0},{"client_id":10598,"income":27943.0},{"client_id":255,"income":22263.0},{"client_id":2375,"income":30261.0},{"client_id":9829,"income":28587.0},{"client_id":6214,"income":43815.0},{"client_id":4954,"income":48195.0},{"client_id":7861,"income":77027.0},{"client_id":4837,"income":71322.0},{"client_id":9423,"income":32765.0},{"client_id":4198,"income":29672.0},{"client_id":153,"income":23272.0},{"client_id":9323,"income":49912.0},{"client_id":10001,"income":7500.0},{"client_id":3945,"income":68117.0},{"client_id":3799,"income":67225.0},{"client_id":8625,"income":17649.0},{"client_id":3491,"income":55914.0},{"client_id":983,"income":40059.0},{"client_id":9119,"income":60905.0},{"client_id":4786,"income":75330.0},{"client_id":5872,"income":60689.0},{"client_id":6568,"income":38680.0},{"client_id":5628,"income":61416.0},{"client_id":5631,"income":49767.0},{"client_id":4974,"income":83273.0},{"client_id":8416,"income":29009.0},{"client_id":5454,"income":45057.0},{"client_id":4095,"income":37150.0},{"client_id":5474,"income":43020.0},{"client_id":4268,"income":53154.0},{"client_id":10701,"income":65308.0},{"client_id":3507,"income":76467.0},{"client_id":2079,"income":81044.0},{"client_id":626,"income":32871.0},{"client_id":4426,"income":55801.0},{"client_id":2591,"income":76320.0},{"client_id":10509,"income":36927.0},{"client_id":6382,"income":48794.0},{"client_id":6673,"income":23478.0},{"client_id":7441,"income":71128.0},{"client_id":1071,"income":70179.0},{"client_id":10061,"income":59462.0},{"client_id":7187,"income":null},{"client_id":8775,"income":38361.0},{"client_id":1612,"income":null},{"client_id":2345,"income":70038.0},{"client_id":322,"income":42554.0},{"client_id":10897,"income":67445.0},{"client_id":123,"income":67046.0},{"client_id":6103,"income":42192.0},{"client_id":7899,"income":77610.0},{"client_id":10500,"income":31761.0},{"client_id":1655,"income":34350.0},{"client_id":2406,"income":54591.0},{"client_id":2712,"income":71866.0},{"client_id":5517,"income":25293.0},{"client_id":10643,"income":42000.0},{"client_id":2254,"income":69520.0},{"client_id":10281,"income":64713.0},{"client_id":6958,"income":27889.0},{"client_id":954,"income":22123.0},{"client_id":5079,"income":null},{"client_id":10339,"income":null},{"client_id":4643,"income":27803.0},{"client_id":3117,"income":null},{"client_id":6497,"income":51651.0},{"client_id":5396,"income":68487.0},{"client_id":5250,"income":null},{"client_id":1052,"income":56796.0},{"client_id":2802,"income":87000.0},{"client_id":6343,"income":79823.0},{"client_id":6507,"income":30828.0},{"client_id":7901,"income":34109.0},{"client_id":4865,"income":53367.0},{"client_id":2686,"income":22390.0},{"client_id":3107,"income":71322.0},{"client_id":7734,"income":79244.0},{"client_id":1146,"income":49912.0},{"client_id":11031,"income":48699.0},{"client_id":7428,"income":80144.0},{"client_id":975,"income":54252.0},{"client_id":1103,"income":81929.0},{"client_id":3422,"income":76068.0},{"client_id":1055,"income":53204.0},{"client_id":6544,"income":67911.0},{"client_id":1241,"income":14796.0},{"client_id":2909,"income":78128.0},{"client_id":5802,"income":14188.0},{"client_id":1407,"income":20425.0},{"client_id":6183,"income":58646.0},{"client_id":340,"income":72967.0},{"client_id":5991,"income":48150.0},{"client_id":3104,"income":82332.0},{"client_id":9729,"income":58275.0},{"client_id":1008,"income":44953.0},{"client_id":11091,"income":34587.0},{"client_id":3969,"income":43018.0},{"client_id":1916,"income":45736.0},{"client_id":9907,"income":66476.0},{"client_id":87,"income":27733.0},{"client_id":8659,"income":69805.0},{"client_id":6262,"income":72217.0},{"client_id":6147,"income":25818.0},{"client_id":8832,"income":37509.0},{"client_id":10067,"income":25176.0},{"client_id":7532,"income":43586.0},{"client_id":4915,"income":53230.0},{"client_id":2115,"income":50116.0},{"client_id":2088,"income":84906.0},{"client_id":2493,"income":61286.0},{"client_id":6292,"income":82333.0},{"client_id":1631,"income":65220.0},{"client_id":10104,"income":33590.0},{"client_id":3006,"income":30992.0},{"client_id":3919,"income":72309.0},{"client_id":11181,"income":156924.0},{"client_id":642,"income":16005.0},{"client_id":4369,"income":65487.0},{"client_id":10127,"income":58692.0},{"client_id":271,"income":40590.0},{"client_id":4973,"income":20587.0},{"client_id":2948,"income":62637.0},{"client_id":2715,"income":29435.0},{"client_id":10432,"income":19346.0},{"client_id":9216,"income":35788.0},{"client_id":7124,"income":36997.0},{"client_id":9727,"income":23539.0},{"client_id":5136,"income":65333.0},{"client_id":9790,"income":78499.0},{"client_id":1818,"income":29732.0},{"client_id":1100,"income":41275.0},{"client_id":7873,"income":63516.0},{"client_id":10609,"income":42769.0},{"client_id":6950,"income":49572.0},{"client_id":7233,"income":69209.0},{"client_id":9481,"income":17148.0},{"client_id":7699,"income":40590.0},{"client_id":2711,"income":30560.0},{"client_id":8933,"income":32146.0},{"client_id":8726,"income":41713.0},{"client_id":1515,"income":34176.0},{"client_id":5186,"income":58482.0},{"client_id":10157,"income":59686.0},{"client_id":5667,"income":60896.0},{"client_id":902,"income":62994.0},{"client_id":977,"income":47320.0},{"client_id":7313,"income":74859.0},{"client_id":7600,"income":15253.0},{"client_id":9706,"income":31560.0},{"client_id":2429,"income":72071.0},{"client_id":3520,"income":91172.0},{"client_id":10394,"income":90000.0},{"client_id":4548,"income":41967.0},{"client_id":9362,"income":69263.0},{"client_id":3968,"income":65706.0},{"client_id":4084,"income":60934.0},{"client_id":6721,"income":71965.0},{"client_id":2829,"income":65210.0},{"client_id":1772,"income":79174.0},{"client_id":1544,"income":81380.0},{"client_id":492,"income":48432.0},{"client_id":4377,"income":52914.0},{"client_id":4541,"income":38946.0},{"client_id":1321,"income":26067.0},{"client_id":8858,"income":44325.0},{"client_id":3266,"income":42523.0},{"client_id":11187,"income":26487.0},{"client_id":8207,"income":53233.0},{"client_id":9723,"income":67716.0},{"client_id":2666,"income":76234.0},{"client_id":5721,"income":84117.0},{"client_id":10652,"income":65487.0},{"client_id":1646,"income":25224.0},{"client_id":4418,"income":89616.0},{"client_id":2656,"income":40851.0},{"client_id":7990,"income":27469.0},{"client_id":8722,"income":82347.0},{"client_id":7118,"income":73803.0},{"client_id":2980,"income":8820.0},{"client_id":1839,"income":43322.0},{"client_id":10722,"income":55593.0},{"client_id":2632,"income":50501.0},{"client_id":9014,"income":37085.0},{"client_id":7620,"income":16185.0},{"client_id":10968,"income":57731.0},{"client_id":11133,"income":48432.0},{"client_id":2736,"income":73807.0},{"client_id":1876,"income":18929.0},{"client_id":5959,"income":35893.0},{"client_id":1092,"income":61014.0},{"client_id":4333,"income":32144.0},{"client_id":3850,"income":14918.0},{"client_id":6168,"income":45146.0},{"client_id":607,"income":41769.0},{"client_id":10469,"income":88325.0},{"client_id":6983,"income":38054.0},{"client_id":3661,"income":80617.0},{"client_id":9303,"income":5305.0},{"client_id":692,"income":36807.0},{"client_id":736,"income":28427.0},{"client_id":9589,"income":82032.0},{"client_id":4838,"income":22775.0},{"client_id":9246,"income":40101.0},{"client_id":6261,"income":58025.0},{"client_id":7366,"income":75777.0},{"client_id":10659,"income":7500.0},{"client_id":1448,"income":33562.0},{"client_id":4286,"income":57642.0},{"client_id":4749,"income":58554.0},{"client_id":4478,"income":63777.0},{"client_id":4201,"income":57967.0},{"client_id":8720,"income":null},{"client_id":10084,"income":24434.0},{"client_id":7004,"income":11012.0},{"client_id":9817,"income":44802.0},{"client_id":8080,"income":26816.0},{"client_id":9432,"income":666666.0},{"client_id":8372,"income":34421.0},{"client_id":10870,"income":61223.0},{"client_id":4001,"income":64014.0},{"client_id":7270,"income":56981.0},{"client_id":8235,"income":69245.0},{"client_id":9405,"income":52869.0}]